intelliparse/__init__.py
intelliparse/parsers.py
intelliparse/py.typed
intelliparse/types.py
intelliparse/images/__init__.py
intelliparse/images/casting.py
intelliparse-0.0.5.dist-info/METADATA
intelliparse-0.0.5.dist-info/WHEEL
intelliparse-0.0.5.dist-info/entry_points.txt
intelliparse-0.0.5.dist-info/licenses/LICENSE
intelliparse-0.0.5.dist-info/RECORD
