Metadata-Version: 2.4
Name: intelliparse
Version: 0.0.5
Summary: Intelliparse is your all-in-one solution to extract text, images, tables, and metadata from **various file formats** - from common documents to complex CAD drawings. Powered by AI for intelligent content understanding.
Author-email: Arthur Brenno <64020210+arthurbrenno@users.noreply.github.com>
License-File: LICENSE
Requires-Python: >=3.13
Requires-Dist: aiofiles>=24.1.0
Requires-Dist: architecture>=0.5.45
Requires-Dist: intellibricks>=0.7.24
Requires-Dist: msgspec>=0.19.0
Requires-Dist: openpyxl>=3.1.5
Requires-Dist: pymupdf>=1.25.2
Requires-Dist: pypdf>=5.2.0
Requires-Dist: python-docx>=1.1.2
Requires-Dist: python-magic>=0.4.27
Requires-Dist: python-pptx>=1.0.2
Requires-Dist: rarfile>=4.2
